sphinxcontrib_prefectviz-0.2.0-py3.9-nspkg.pth
sphinxcontrib/prefectviz/__init__.py
sphinxcontrib/prefectviz/flowviz.py
sphinxcontrib_prefectviz-0.2.0.dist-info/AUTHORS
sphinxcontrib_prefectviz-0.2.0.dist-info/LICENSE
sphinxcontrib_prefectviz-0.2.0.dist-info/METADATA
sphinxcontrib_prefectviz-0.2.0.dist-info/WHEEL
sphinxcontrib_prefectviz-0.2.0.dist-info/namespace_packages.txt
sphinxcontrib_prefectviz-0.2.0.dist-info/pbr.json
sphinxcontrib_prefectviz-0.2.0.dist-info/top_level.txt
sphinxcontrib_prefectviz-0.2.0.dist-info/RECORD
